spoon_ai/__init__.py
spoon_ai/chat.py
spoon_ai/graph.py
spoon_ai/schema.py
spoon_ai/agents/__init__.py
spoon_ai/agents/base.py
spoon_ai/agents/custom_agent.py
spoon_ai/agents/graph_agent.py
spoon_ai/agents/mcp_client_mixin.py
spoon_ai/agents/monitor.py
spoon_ai/agents/rag.py
spoon_ai/agents/react.py
spoon_ai/agents/spoon_react.py
spoon_ai/agents/spoon_react_mcp.py
spoon_ai/agents/toolcall.py
spoon_ai/bridge/__init__.py
spoon_ai/bridge/eth_neofs_indexer.py
spoon_ai/callbacks/__init__.py
spoon_ai/callbacks/base.py
spoon_ai/callbacks/manager.py
spoon_ai/callbacks/statistics.py
spoon_ai/callbacks/stream_event.py
spoon_ai/callbacks/streaming_stdout.py
spoon_ai/graph/__init__.py
spoon_ai/graph/agent.py
spoon_ai/graph/builder.py
spoon_ai/graph/checkpointer.py
spoon_ai/graph/config.py
spoon_ai/graph/decorators.py
spoon_ai/graph/engine.py
spoon_ai/graph/exceptions.py
spoon_ai/graph/mcp_integration.py
spoon_ai/graph/reducers.py
spoon_ai/graph/types.py
spoon_ai/identity/__init__.py
spoon_ai/identity/attestation.py
spoon_ai/identity/did_models.py
spoon_ai/identity/did_resolver.py
spoon_ai/identity/erc8004_abi.py
spoon_ai/identity/erc8004_client.py
spoon_ai/identity/storage_client.py
spoon_ai/llm/__init__.py
spoon_ai/llm/base.py
spoon_ai/llm/cache.py
spoon_ai/llm/config.py
spoon_ai/llm/errors.py
spoon_ai/llm/factory.py
spoon_ai/llm/interface.py
spoon_ai/llm/manager.py
spoon_ai/llm/monitoring.py
spoon_ai/llm/registry.py
spoon_ai/llm/response_normalizer.py
spoon_ai/llm/providers/__init__.py
spoon_ai/llm/providers/anthropic_provider.py
spoon_ai/llm/providers/deepseek_provider.py
spoon_ai/llm/providers/gemini_provider.py
spoon_ai/llm/providers/ollama_provider.py
spoon_ai/llm/providers/openai_compatible_provider.py
spoon_ai/llm/providers/openai_provider.py
spoon_ai/llm/providers/openrouter_provider.py
spoon_ai/llm/vlm_provider/base.py
spoon_ai/llm/vlm_provider/gemini.py
spoon_ai/memory/__init__.py
spoon_ai/memory/mem0_client.py
spoon_ai/memory/remove_message.py
spoon_ai_sdk-0.3.6.dist-info/licenses/LICENSE
spoon_ai_sdk-0.3.6.dist-info/METADATA
spoon_ai_sdk-0.3.6.dist-info/WHEEL
spoon_ai_sdk-0.3.6.dist-info/top_level.txt
spoon_ai_sdk-0.3.6.dist-info/RECORD
