Metadata-Version: 2.4
Name: spoon-ai-sdk
Version: 0.3.6
Summary: SDK for SpoonAI tools and agents
Author-email: Your Name <your.email@example.com>
Project-URL: Homepage, https://github.com/XSpoonAi/spoon-core
Project-URL: Bug Tracker, https://github.com/XSpoonAi/spoon-core/issues
Classifier: Programming Language :: Python :: 3
Classifier: License :: OSI Approved :: MIT License
Classifier: Operating System :: OS Independent
Requires-Python: >=3.12
License-File: LICENSE
Requires-Dist: aiohappyeyeballs>=2.4.4
Requires-Dist: aiohttp>=3.13.2
Requires-Dist: pycares<5.0,>=4.9
Requires-Dist: aiosignal>=1.3.2
Requires-Dist: annotated-types>=0.7.0
Requires-Dist: anyio>=4.8.0
Requires-Dist: attrs>=25.1.0
Requires-Dist: certifi>=2025.1.31
Requires-Dist: charset-normalizer>=3.4.1
Requires-Dist: distro>=1.9.0
Requires-Dist: fastapi>=0.115.7
Requires-Dist: frozenlist>=1.5.0
Requires-Dist: greenlet>=3.1.1
Requires-Dist: h11>=0.14.0
Requires-Dist: httpcore>=1.0.7
Requires-Dist: httpx>=0.28.1
Requires-Dist: idna>=3.10
Requires-Dist: jiter>=0.5.0
Requires-Dist: jsonpointer>=3.0.0
Requires-Dist: multidict>=6.1.0
Requires-Dist: openai>=1.70.0
Requires-Dist: orjson>=3.10.15
Requires-Dist: propcache>=0.2.1
Requires-Dist: pydantic>=2.10.4
Requires-Dist: pydantic-core>=2.27.2
Requires-Dist: python-dotenv>=1.0.1
Requires-Dist: regex>=2024.11.6
Requires-Dist: requests>=2.32.3
Requires-Dist: requests-toolbelt>=1.0.0
Requires-Dist: sniffio>=1.3.1
Requires-Dist: sqlalchemy>=2.0.38
Requires-Dist: starlette>=0.45.3
Requires-Dist: tenacity>=8.5.0
Requires-Dist: tiktoken>=0.8.0
Requires-Dist: tqdm>=4.67.1
Requires-Dist: typing-extensions>=4.12.2
Requires-Dist: urllib3>=2.3.0
Requires-Dist: yarl>=1.18.3
Requires-Dist: websockets==15.0.1
Requires-Dist: termcolor>=3.0.1
Requires-Dist: pinecone>=6.0.2
Requires-Dist: google>=3.0.0
Requires-Dist: google-genai>=1.11.0
Requires-Dist: protobuf>=3.19.5
Requires-Dist: google-api-core>=2.24.2
Requires-Dist: grpcio>=1.71.0
Requires-Dist: neo-mamba<3.2.0,>=3.0.1; python_version < "3.14"
Requires-Dist: neo-mamba>=3.2.0; python_version == "3.14"
Requires-Dist: web3==7.11.0
Requires-Dist: nest-asyncio>=1.6.0
Requires-Dist: anthropic>=0.42.0
Requires-Dist: boto3==1.35.99
Requires-Dist: botocore==1.35.99
Requires-Dist: fastmcp>=2.12.0
Requires-Dist: googleapis-common-protos
Requires-Dist: cryptography>=41.0.0
Requires-Dist: eth-utils>=2.0.0
Requires-Dist: rlp>=3.0.0
Requires-Dist: uvicorn[standard]>=0.32.0
Requires-Dist: x402>=1.0.0
Provides-Extra: memory
Requires-Dist: mem0ai>=0.0.1; extra == "memory"
Dynamic: license-file
